pysabnzbd/__init__.py
pysabnzbd-1.1.0.dist-info/LICENSE
pysabnzbd-1.1.0.dist-info/METADATA
pysabnzbd-1.1.0.dist-info/WHEEL
pysabnzbd-1.1.0.dist-info/top_level.txt
pysabnzbd-1.1.0.dist-info/RECORD
