Metadata-Version: 2.1
Name: pysabnzbd
Version: 1.1.0
Summary: Python wrapper for SABnzbd API
Home-page: https://github.com/jeradM/pysabnzbd
Download-URL: https://github.com/jeradM/pysabnzbd/archive/1.1.0.tar.gz
Author: Jerad Meisner
Author-email: jerad.meisner@gmail.com
License: UNKNOWN
Keywords: SABnzbd
Platform: UNKNOWN
License-File: LICENSE
Requires-Dist: aiohttp
Requires-Dist: async-timeout
